{
  "schema_version": "1.0.0",
  "evidence_pack_id": "family-surg-hidradenitis",
  "family_name": "General Surgery — Hidradenitis surgical review",
  "workflow_ids": [
    "surg-hidradenitis-surgical-review"
  ],
  "clinical_scope": "Hidradenitis surgical review",
  "population": "People with relevant hidradenitis surgical review history, findings and clinician decisions entered.",
  "intended_setting": "Partial for hidradenitis presentation and baseline assessment; surgical selection and UAE pathways remain unsupported.",
  "exclusions": [],
  "special_cases": [],
  "source_hierarchy": {
    "uae": [],
    "governmental": [],
    "professional": []
  },
  "source_ids": [
    "bad-hidradenitis-suppurativa-guideline-2018"
  ],
  "usable_source_ids": [],
  "structurally_limited_source_ids": [],
  "blocked_source_ids": [
    "bad-hidradenitis-suppurativa-guideline-2018"
  ],
  "source_conflicts": [],
  "evidence_statements": [],
  "section_coverage": {
    "red_flags": "no_authoritative_guidance_found",
    "escalation": "no_authoritative_guidance_found",
    "investigations": "no_authoritative_guidance_found",
    "management": "no_authoritative_guidance_found",
    "follow_up": "no_authoritative_guidance_found",
    "patient_advice": "no_authoritative_guidance_found",
    "assessment": "no_authoritative_guidance_found"
  },
  "pack_status": "additional_corpus_search_required",
  "input_fingerprint": "aee9d54bf0a5bd6df95b94c533344f7797fbffe7435c1c6b985675cecf41c3d9",
  "evidence_pack_fingerprint": "4f53cda18c2baa0c0354bb5f9a3ecbe5ed12ab4d8e11ba873c2f11161202b945"
}
